image_operations/__init__.py
image_operations/channels.py
image_operations/fliping_image.py
image_operations-0.0.1.dist-info/METADATA
image_operations-0.0.1.dist-info/WHEEL
image_operations-0.0.1.dist-info/top_level.txt
image_operations-0.0.1.dist-info/RECORD
