Metadata-Version: 2.1
Name: image-operations
Version: 0.0.1
Summary: Exercice about packages - Bootcamp Data Science Unimed
Home-page: https://github.com/celsolearner/image-operations
Author: celso
Author-email: celsolearner@gmail.com
License: UNKNOWN
Platform: UNKNOWN
Requires-Python: >=3.0
Requires-Dist: matplotlib
Requires-Dist: pillow
